CHANGELOG.md
LICENSE
allianceutils/__init__.py
allianceutils/api/__init__.py
allianceutils/api/mixins.py
allianceutils/api/parsers.py
allianceutils/api/permissions.py
allianceutils/api/renderers.py
allianceutils/apps.py
allianceutils/auth/__init__.py
allianceutils/auth/backends.py
allianceutils/auth/models.py
allianceutils/auth/permission.py
allianceutils/bin/internaldeps.sh
allianceutils/checks.py
allianceutils/decorators.py
allianceutils/management/__init__.py
allianceutils/management/commands/__init__.py
allianceutils/management/commands/base.py
allianceutils/management/commands/document_reverse_accessors.py
allianceutils/management/commands/print_logging.py
allianceutils/middleware/__init__.py
allianceutils/middleware/current_request.py
allianceutils/middleware/current_user.py
allianceutils/middleware/http_auth.py
allianceutils/middleware/query_count.py
allianceutils/migrations.py
allianceutils/models.py
allianceutils/py.typed
allianceutils/rules.py
allianceutils/serializers/__init__.py
allianceutils/serializers/json_ordered.py
allianceutils/template.py
allianceutils/templatetags/__init__.py
allianceutils/templatetags/alliance_webpack.py
allianceutils/templatetags/default_value.py
allianceutils/tests/util.py
allianceutils/util/__init__.py
allianceutils/util/camel_case.py
allianceutils/util/date.py
allianceutils/util/get_firstparty_apps.py
allianceutils/util/strtobool.py
allianceutils/views/__init__.py
allianceutils/views/decorators.py
allianceutils/webpack.py
django_allianceutils-4.2.1.dist-info/LICENSE
django_allianceutils-4.2.1.dist-info/METADATA
django_allianceutils-4.2.1.dist-info/WHEEL
django_allianceutils-4.2.1.dist-info/RECORD
