Metadata-Version: 2.1
Name: django-allianceutils
Version: 4.2.1
Summary: Alliance Software common utilities for Django
Home-page: https://github.com/AllianceSoftware/django-allianceutils/
License: BSD-2-Clause
Keywords: django,alliance,alliancesoftware
Author: Alliance Software
Author-email: support@alliancesoftware.com.au
Requires-Python: >=3.8,<4.0
Classifier: Development Status :: 5 - Production/Stable
Classifier: Environment :: Web Environment
Classifier: Framework :: Django
Classifier: Framework :: Django :: 4.2
Classifier: Framework :: Django :: 5.0
Classifier: Intended Audience :: Developers
Classifier: License :: OSI Approved :: BSD License
Classifier: Operating System :: MacOS
Classifier: Operating System :: POSIX :: Linux
Classifier: Programming Language :: Python :: 3
Classifier: Programming Language :: Python :: 3.8
Classifier: Programming Language :: Python :: 3.9
Classifier: Programming Language :: Python :: 3.10
Classifier: Programming Language :: Python :: 3.11
Classifier: Programming Language :: Python :: 3.12
Classifier: Programming Language :: Python :: 3.13
Classifier: Programming Language :: Python :: 3 :: Only
Classifier: Typing :: Typed
Provides-Extra: extras
Provides-Extra: mysql
Provides-Extra: postgres
Requires-Dist: isort (>=5) ; extra == "extras"
Requires-Dist: logging_tree ; extra == "extras"
Requires-Dist: mysqlclient ; extra == "mysql"
Requires-Dist: psycopg ; extra == "postgres"
Requires-Dist: rules ; extra == "extras"
Requires-Dist: typing_extensions (>=4.5.0,<5.0.0)
Project-URL: Documentation, https://github.com/AllianceSoftware/django-allianceutils/blob/master/README.md
Project-URL: Repository, https://github.com/AllianceSoftware/django-allianceutils/
Project-URL: issues, https://github.com/AllianceSoftware/django-allianceutils/issues
